greyhorse_elasticsearch/__init__.py
greyhorse_elasticsearch/config.py
greyhorse_elasticsearch/contexts.py
greyhorse_elasticsearch/engine.py
greyhorse_elasticsearch/factory.py
greyhorse_elasticsearch/service.py
greyhorse_elasticsearch/translations.toml
greyhorse_elasticsearch-0.2.1.dist-info/METADATA
greyhorse_elasticsearch-0.2.1.dist-info/WHEEL
greyhorse_elasticsearch-0.2.1.dist-info/RECORD
